fable3d-1.1.4.dist-info/licenses/LICENSE
my3dengine/UI.py
my3dengine/__init__.py
my3dengine/audio.py
my3dengine/camera.py
my3dengine/core.py
my3dengine/key.py
my3dengine/mesh.py
my3dengine/scene.py
my3dengine/sdl2.dll
my3dengine/shader.py
fable3d-1.1.4.dist-info/METADATA
fable3d-1.1.4.dist-info/WHEEL
fable3d-1.1.4.dist-info/top_level.txt
fable3d-1.1.4.dist-info/RECORD
